datareg/__init__.py
datareg/tensorflow/__init__.py
datareg/tensorflow/vision/__init__.py
datareg/tensorflow/vision/layers.py
datareg-0.3.0.dist-info/METADATA
datareg-0.3.0.dist-info/WHEEL
datareg-0.3.0.dist-info/top_level.txt
datareg-0.3.0.dist-info/RECORD
