Metadata-Version: 2.4
Name: datareg
Version: 0.3.0
Summary: Data regularization layers
Author-email: Umberto Barros <umbertobarrosf@gmail.com>
License: MIT
Classifier: Programming Language :: Python :: 3
Classifier: License :: OSI Approved :: MIT License
Classifier: Operating System :: OS Independent
Requires-Python: >=3.8
Requires-Dist: tensorflow>=2.12.0
Requires-Dist: keras-cv>=0.6.0
